boj/__init__.py
boj/__main__.py
boj/args_resolver.py
boj/containers.py
boj/entry.py
boj/browsers/login_browser.py
boj/commands/__init__.py
boj/commands/add/__init__.py
boj/commands/add/command.py
boj/commands/case/__init__.py
boj/commands/case/command.py
boj/commands/clean/__init__.py
boj/commands/clean/command.py
boj/commands/init/__init__.py
boj/commands/init/command.py
boj/commands/login/__init__.py
boj/commands/login/command.py
boj/commands/open/__init__.py
boj/commands/open/command.py
boj/commands/random/__init__.py
boj/commands/random/command.py
boj/commands/run/__init__.py
boj/commands/run/command.py
boj/commands/run/runner.py
boj/commands/submit/__init__.py
boj/commands/submit/command.py
boj/commands/submit/progress_message.py
boj/commands/submit/websocket.py
boj/core/__init__.py
boj/core/browser.py
boj/core/command.py
boj/core/console.py
boj/core/constant.py
boj/core/crypto.py
boj/core/error.py
boj/core/html.py
boj/core/http.py
boj/core/fs/__init__.py
boj/core/fs/file_io.py
boj/core/fs/file_object.py
boj/core/fs/file_search_strategy.py
boj/core/fs/repository.py
boj/core/fs/serializer.py
boj/core/fs/util.py
boj/data/__init__.py
boj/data/boj_info.py
boj/data/config.py
boj/data/credential.py
boj/data/session.py
boj/data/testcase.py
boj/web/__init__.py
boj/web/boj_main_page.py
boj/web/boj_problem_page.py
boj/web/boj_status_page.py
boj/web/boj_submit_page.py
boj/web/solved_ac_search_api.py
boj_cli-1.2.14.dist-info/LICENSE
boj_cli-1.2.14.dist-info/METADATA
boj_cli-1.2.14.dist-info/WHEEL
boj_cli-1.2.14.dist-info/entry_points.txt
boj_cli-1.2.14.dist-info/top_level.txt
boj_cli-1.2.14.dist-info/RECORD
