Metadata-Version: 2.2
Name: boj-cli
Version: 1.2.14
Summary: Command line interface for BOJ
Author: xvzc
Requires-Python: <3.14,>=3.10.17
License-File: LICENSE
Requires-Dist: beautifulsoup4<5.0.0,>=4.11.1
Requires-Dist: cryptography<40.0.0,>=39.0.0
Requires-Dist: selenium<5.0.0,>=4.28.1
Requires-Dist: requests<3.0.0,>=2.28.2
Requires-Dist: rich<14.0.0,>=13.2.0
Requires-Dist: dependency-injector<5.0.0,>=4.45.0
Requires-Dist: websockets<11.0,>=10.4
Requires-Dist: PyYAML!=5.4.0,!=5.4.1,<6.0.0,>=5.3.1
Provides-Extra: dev
Requires-Dist: pynvim; extra == "dev"
Requires-Dist: black; extra == "dev"
Requires-Dist: pytest; extra == "dev"
Requires-Dist: pytest-mock; extra == "dev"
Provides-Extra: test
Requires-Dist: pytest; extra == "test"
Requires-Dist: pytest-mock; extra == "test"
